<DOMSymbolItem xmlns:xsi="http://www.w3.org/2001/XMLSchema-instance" xmlns="http://ns.adobe.com/xfl/2008/" name="sav44" itemID="5062f28b-000002b4" symbolType="button" lastModified="1348661899">
  <timeline>
    <DOMTimeline name="sav44">
      <layers>
        <DOMLayer name="Layer 1" color="#4FFF4F" current="true" isSelected="true">
          <frames>
            <DOMFrame index="0" keyMode="9728">
              <elements>
                <DOMShape>
                  <fills>
                    <FillStyle index="1">
                      <BitmapFill bitmapPath="Savivaldybiu_konturai.png" bitmapIsClipped="false">
                        <matrix>
                          <Matrix a="20" d="20" tx="-374.45" ty="-312.85"/>
                        </matrix>
                      </BitmapFill>
                    </FillStyle>
                  </fills>
                  <edges>
                    <Edge fillStyle1="1" edges="!858 223S2[858 230 858 237!858 237[857 240 856 244!856 244[837 307 871 323!871 323[945 379 959 267!959 267[961 253 991 243!991 243[1059 290 981 355!981 355[971 363 971 383!971 383[1032 402 1051 463!1051 463[1041 503 1012 525!1012 525
[1001 533 991 543!991 543[950 552 891 563!891 563[850 490 811 563!811 563[786 608 747 638!747 638[741 643 731 643!731 643[678 719 687 764!687 764[691 783 691 803!691 803[628 799 661 843!661 843|651 843!651 843[620 851 589 859!589 859
[579 858 569 858!569 858[543 807 471 803!471 803[463 855 392 839!392 839[187 793 71 803!71 803[-28 877 11 783!11 783[-14 685 61 595!61 595[65 591 67 586!67 586[74 582 79 577!79 577[91 567 102 558!102 558[144 548 171 523!171 523[191 483
 214 445!214 445[221 433 231 423!231 423[231 393 231 363!231 363[231 343 231 323!231 323[269 310 189 299!189 299[133 292 151 223!151 223[220 306 291 203!291 203[353 188 467 233!467 233[547 264 611 203!611 203[625 129 601 96!601 96[591
 83 591 63!591 63[619 11 691 3!691 3[752 -17 781 86!781 86[792 122 811 143!811 143[877 112 869 187!869 187[865 191 864 196!864 196|862 199!862 199[859 207 858 217!858 217|858 223"/>
                  </edges>
                </DOMShape>
              </elements>
            </DOMFrame>
          </frames>
        </DOMLayer>
      </layers>
    </DOMTimeline>
  </timeline>
</DOMSymbolItem>